starty/__init__.py
starty/cli.py
starty/utils.py
starty-0.0.1.dist-info/METADATA
starty-0.0.1.dist-info/WHEEL
starty-0.0.1.dist-info/entry_points.txt
starty-0.0.1.dist-info/top_level.txt
starty-0.0.1.dist-info/RECORD
